taggie/__init__.py
taggie/__main__.py
taggie/_version.py
taggie/main.py
taggie/defaults/__init__.py
taggie/defaults/css.yaml
taggie/defaults/detect-secrets.yaml
taggie/defaults/git.yaml
taggie/defaults/gitlab.yaml
taggie/defaults/golang.yaml
taggie/defaults/html.yaml
taggie/defaults/javascript.yaml
taggie/defaults/jinja.yaml
taggie/defaults/json.yaml
taggie/defaults/jsonl.yaml
taggie/defaults/license-eye.yaml
taggie/defaults/license.yaml
taggie/defaults/make.yaml
taggie/defaults/markdown.yaml
taggie/defaults/mkdocs.yaml
taggie/defaults/opentofu.yaml
taggie/defaults/pdf.yaml
taggie/defaults/pre_commit.yaml
taggie/defaults/prettier.yaml
taggie/defaults/python.yaml
taggie/defaults/readme.yaml
taggie/defaults/restructuredtext.yaml
taggie/defaults/rust.yaml
taggie/defaults/shell.yaml
taggie/defaults/sql.yaml
taggie/defaults/toml.yaml
taggie/defaults/typescript.yaml
taggie/defaults/xml.yaml
taggie/defaults/yaml.yaml
taggie/reports/__init__.py
taggie/reports/json_report.py
taggie/reports/table_report.py
taggie/taggers/__init__.py
taggie/taggers/_base.py
taggie/taggers/_files.py
taggie/taggers/file_extension.py
taggie/taggers/file_name.py
taggie-0.5.0.dist-info/licenses/LICENSE
taggie-0.5.0.dist-info/licenses/NOTICE
taggie-0.5.0.dist-info/METADATA
taggie-0.5.0.dist-info/WHEEL
taggie-0.5.0.dist-info/entry_points.txt
taggie-0.5.0.dist-info/top_level.txt
taggie-0.5.0.dist-info/RECORD
