Metadata-Version: 2.4
Name: taggie
Version: 0.5.0
Summary: It's like Badgie but for tags!
Author-email: Digital Safety Research Institute <contact@dsri.org>
License: Apache-2.0
Project-URL: Home, https://gitlab.com/saferatday0/sandbox/taggie
Project-URL: Issues, https://gitlab.com/saferatday0/sandbox/taggie/-/issues
Classifier: Development Status :: 1 - Planning
Classifier: Intended Audience :: Developers
Classifier: Programming Language :: Python :: 3
Classifier: Programming Language :: Python :: 3.9
Classifier: Programming Language :: Python :: 3.10
Classifier: Programming Language :: Python :: 3.11
Classifier: Programming Language :: Python :: 3.12
Classifier: Programming Language :: Python :: 3.13
Requires-Python: >=3.9
License-File: LICENSE
License-File: NOTICE
Requires-Dist: msgspec[yaml]
Requires-Dist: tabulate
Dynamic: license-file
